pswdclient
