Metadata-Version: 1.1
Name: pswdclient
Version: 0.3.1
Summary: A client library for Google App Engine integration with pswdless.appspot.com
Home-page: https://github.com/renzon/pswdclient
Author: Renzo Nuccitelli
Author-email: renzo.n@gmail.com
License: BSD
Platform: UNKNOWN
Classifier: Development Status :: 4 - Beta
Classifier: Environment :: Web Environment
Classifier: Intended Audience :: Developers
Classifier: License :: OSI Approved :: BSD License
Classifier: Operating System :: OS Independent
Classifier: Programming Language :: Python
Classifier: Framework :: Paste
